.editorconfig
LICENSE
Pipfile
Pipfile.lock
README.md
example.png
setup.cfg
setup.py
bin/index-hr
indexhr/__about__.py
indexhr/__init__.py
indexhr/scrapper.py
indexhr/utils.py
indexhr.egg-info/PKG-INFO
indexhr.egg-info/SOURCES.txt
indexhr.egg-info/dependency_links.txt
indexhr.egg-info/not-zip-safe
indexhr.egg-info/pbr.json
indexhr.egg-info/requires.txt
indexhr.egg-info/top_level.txt