Metadata-Version: 2.1
Name: indexhr
Version: 0.7.1
Summary: index.hr basic news content in the terminal
Home-page: https://github.com/marinko-peso/index-hr/
Author: Marinko Peso
Author-email: marinko.peso@gmail.com
License: MIT
Keywords: index hr terminal cli news croatia
Platform: UNKNOWN
Classifier: Intended Audience :: Developers
Classifier: License :: OSI Approved :: MIT License
Classifier: Operating System :: OS Independent
Classifier: Programming Language :: Python
Classifier: Programming Language :: Python :: 2
Classifier: Programming Language :: Python :: 2.7
Classifier: Programming Language :: Python :: 3
Classifier: Programming Language :: Python :: 3.6
